{"name":"PAC20131","tagline":"Projeto de Arquitetura de Computadores 2013.1 ","body":"Este projeto é fruto de um trabalho de conclusão da disciplina de Arquitetura de Computadores I, ministrada na Universidade Federal de Sergipe, campus São Cristóvão. \r\nNo período 2013.1 o docente Marco Túlio Chella instigou seus alunos com a proposta de fazer um processador simulado em alguma linguagem de programação, com a finalidade de facilitar o entendimento dos conceitos fundamentais da disciplina. Após exibir vários projetos já feitos pela comunidade acadêmica e por curiosos, relatou a ineficiência das soluções propostas...(continua)","google":"","note":"Don't delete this file! It's used internally to help with page regeneration."}